dot_notation_dict/__init__.py
dot_notation_dict-0.2.0.dist-info/LICENSE
dot_notation_dict-0.2.0.dist-info/METADATA
dot_notation_dict-0.2.0.dist-info/WHEEL
dot_notation_dict-0.2.0.dist-info/RECORD
