Metadata-Version: 2.1
Name: dot_notation_dict
Version: 0.2.0
Summary: A simple package which converts a standard python dictionary to a dot accessible object.
License: LICENCE
Author: AidanInceer
Author-email: aidaninceer0@gmail.com
Requires-Python: >=3.11,<4.0
Classifier: License :: Other/Proprietary License
Classifier: Programming Language :: Python :: 3
Classifier: Programming Language :: Python :: 3.11
Classifier: Programming Language :: Python :: 3.12
Requires-Dist: pre-commit (>=3.7.0,<4.0.0)
